helios/__init__.py
helios/helios.py
helios/stream.py
helios/utils.py
helios_monitor-2.0.1.dist-info/LICENCE.md
helios_monitor-2.0.1.dist-info/METADATA
helios_monitor-2.0.1.dist-info/WHEEL
helios_monitor-2.0.1.dist-info/entry_points.txt
helios_monitor-2.0.1.dist-info/top_level.txt
helios_monitor-2.0.1.dist-info/RECORD
