Metadata-Version: 2.1
Name: helios-monitor
Version: 2.0.1
Summary: Exposes the audio levels of a stream to Prometheus
Home-page: https://salsa.debian.org/debconf-video-team/helios
Author: Kyle Robbertze
Author-email: paddatrapper@debian.org
License: GPL-3
Keywords: streaming audio monitor R128
Classifier: Development Status :: 4 - Beta
Classifier: Intended Audience :: Other Audience
Classifier: Topic :: Multimedia :: Sound/Audio
Classifier: License :: OSI Approved :: GNU General Public License v3 (GPLv3)
Classifier: Programming Language :: Python :: 3
Classifier: Programming Language :: Python :: 3.4
Classifier: Programming Language :: Python :: 3.5
Classifier: Programming Language :: Python :: 3.6
Classifier: Programming Language :: Python :: 3.7
Classifier: Programming Language :: Python :: 3.8
Classifier: Programming Language :: Python :: 3.9
Classifier: Programming Language :: Python :: 3.10
License-File: LICENCE.md
Requires-Dist: prometheus-aioexporter
